{
    "success": true,
    "data": [
        {
            "name": "北京"
        },
        {
            "name": "上海"
        },
        {
            "name": "广州"
        },
        {
            "name": "深圳"
        },
        {
            "name": "南京"
        },
        {
            "name": "武汉"
        },
        {
            "name": "杭州"
        },
        {
            "name": "西安"
        },
        {
            "name": "郑州"
        },
        {
            "name": "成都"
        },
        {
            "name": "长沙"
        },
        {
            "name": "天津"
        }
    ]
}